config_profile/__init__.py
config_profile/config.py
config_profile/dict_util.py
config_profile/file_util.py
config_profile/singleton_util.py
config_profile-0.0.3.dist-info/METADATA
config_profile-0.0.3.dist-info/WHEEL
config_profile-0.0.3.dist-info/licenses/LICENSE
config_profile-0.0.3.dist-info/RECORD
