Metadata-Version: 2.3
Name: config_profile
Version: 0.0.3
Summary: Application configuration made simple
Project-URL: Homepage, https://github.com/avegancafe/config-profile
Project-URL: Issues, https://github.com/avegancafe/config-profile/issues
Author-email: Kyle Holzinger <kyleholzinger@hey.com>, Jamie Cristini <jamie@j2health.com>
License-File: LICENSE
Classifier: License :: OSI Approved :: MIT License
Classifier: Operating System :: OS Independent
Classifier: Programming Language :: Python :: 3
Requires-Python: >=3.12
